[
	{"tier": "1", "id": "1701"},
	{"tier": "1", "id": "4074"},
	{"tier": "1", "id": "4075"},
	{"tier": "1", "id": "5088"},
	{"tier": "1", "id": "5074"},
	{"tier": "1", "id": "6041"},
	{"tier": "1", "id": "6075"},
	{"tier": "1", "id": "6016"},
	
	{"tier": "2", "id": "1702"},
	{"tier": "2", "id": "4090"},
	{"tier": "2", "id": "5001"},
	{"tier": "2", "id": "6043"},
	{"tier": "2", "id": "6001"},
	{"tier": "2", "id": "6004"},
	{"tier": "2", "id": "6090"},
	
	{"tier": "3", "id": "1705"},
	{"tier": "3", "id": "4081"},
	{"tier": "3", "id": "4133"},
	{"tier": "3", "id": "4078"},
	{"tier": "3", "id": "4019"},
	{"tier": "3", "id": "5081"},
	{"tier": "3", "id": "6006"},
	{"tier": "3", "id": "6081"},
	{"tier": "3", "id": "6095"},
	
	{"tier": "4", "id": "1704"},
	{"tier": "4", "id": "1703"},
	{"tier": "4", "id": "4126"},
	{"tier": "4", "id": "5122"},
	{"tier": "4", "id": "5132"},
	{"tier": "4", "id": "6097"},
	{"tier": "4", "id": "6116"},
	{"tier": "4", "id": "6053"},
	
	{"tier": "5", "id": "1707"},
	{"tier": "5", "id": "4131"},
	{"tier": "5", "id": "5090"},
	{"tier": "5", "id": "5075"},
	{"tier": "5", "id": "6060"},
	{"tier": "5", "id": "6078"},
	
	{"tier": "6", "id": "1709"},
	{"tier": "6", "id": "4050"},
	{"tier": "6", "id": "4085"},
	{"tier": "6", "id": "5106"},
	{"tier": "6", "id": "5097"},
	{"tier": "6", "id": "5078"},
	{"tier": "6", "id": "6102"},
	{"tier": "6", "id": "6055"},
	{"tier": "6", "id": "6123"},
	
	{"tier": "7", "id": "1708"},
	{"tier": "7", "id": "4034"},
	{"tier": "7", "id": "5032"},
	{"tier": "7", "id": "6085"},
	
	{"tier": "8", "id": "1803"},
	{"tier": "8", "id": "1801"},
	{"tier": "8", "id": "4083"},
	{"tier": "8", "id": "6032"},
	
	{"tier": "9", "id": "1802"},
	{"tier": "9", "id": "4102"},
	{"tier": "9", "id": "5085"},
	{"tier": "9", "id": "6067"},
	{"tier": "9", "id": "6113"},
	
	{"tier": "10", "id": "1800"},
	{"tier": "10", "id": "4132"},
	{"tier": "10", "id": "4087"},
	{"tier": "10", "id": "5083"},
	{"tier": "10", "id": "6114"},
	{"tier": "10", "id": "6034"},
	
	{"tier": "11", "id": "1706"},
	{"tier": "11", "id": "5129"},
	{"tier": "11", "id": "5131"},
	{"tier": "11", "id": "6115"},
	
	{"tier": "12", "id": "1805"},
	{"tier": "12", "id": "4115"},
	{"tier": "12", "id": "5087"},
	{"tier": "12", "id": "6087"}
]