{
    "SuddenQuestTable01.user": {
        "0": {
            "_AppearNum": [
                1,
                1
            ],
            "_AppearRate": 100,
            "_CharaID": "Minotaur",
            "_GenerateDisableFlag": 255,
            "_Group": "B",
            "_InitSetType": "Wait",
            "_IsDestinationMove": true,
            "_IsFinishCheck": "null",
            "_IsForceCombat": true,
            "_IsThinkStop": false,
            "_IsWanderMove": true,
            "_ManualPos": [
                0.0,
                0.0,
                0.0
            ],
            "_ParamId": 0,
            "_QuestID": "null",
            "_StatusID": "None",
            "_TimeZone": 15
        },
        "1": {
            "_AppearNum": [
                1,
                1
            ],
            "_AppearRate": 100,
            "_CharaID": "Chimera",
            "_GenerateDisableFlag": 255,
            "_Group": "C",
            "_InitSetType": "Wait",
            "_IsDestinationMove": true,
            "_IsFinishCheck": "null",
            "_IsForceCombat": true,
            "_IsThinkStop": false,
            "_IsWanderMove": true,
            "_ManualPos": [
                0.0,
                0.0,
                0.0
            ],
            "_ParamId": 0,
            "_QuestID": "null",
            "_StatusID": "None",
            "_TimeZone": 15
        },
        "2": {
            "_AppearNum": [
                1,
                1
            ],
            "_AppearRate": 100,
            "_CharaID": "Ogre",
            "_GenerateDisableFlag": 255,
            "_Group": "A",
            "_InitSetType": "Wait",
            "_IsDestinationMove": true,
            "_IsFinishCheck": "null",
            "_IsForceCombat": true,
            "_IsThinkStop": false,
            "_IsWanderMove": true,
            "_ManualPos": [
                0.0,
                0.0,
                0.0
            ],
            "_ParamId": 0,
            "_QuestID": "null",
            "_StatusID": "None",
            "_TimeZone": 15
        },
        "A": 99,
        "B": 99,
        "C": 99
    }
}