{
    "SuddenQuestTable15.user": {
        "0": {
            "_AppearNum": [
                1,
                1
            ],
            "_AppearRate": 50,
            "_CharaID": "Wight",
            "_GenerateDisableFlag": 255,
            "_Group": "B",
            "_InitSetType": "Ch228_Ground",
            "_IsDestinationMove": true,
            "_IsFinishCheck": "null",
            "_IsForceCombat": false,
            "_IsThinkStop": false,
            "_IsWanderMove": true,
            "_ManualPos": [
                0.0,
                0.0,
                0.0
            ],
            "_ParamId": 0,
            "_QuestID": "null",
            "_StatusID": "None",
            "_TimeZone": 15
        },
        "1": {
            "_AppearNum": [
                1,
                1
            ],
            "_AppearRate": 100,
            "_CharaID": "SkeletonLord",
            "_GenerateDisableFlag": 255,
            "_Group": "B",
            "_InitSetType": "Ch228_Ground",
            "_IsDestinationMove": true,
            "_IsFinishCheck": "null",
            "_IsForceCombat": false,
            "_IsThinkStop": false,
            "_IsWanderMove": true,
            "_ManualPos": [
                0.0,
                0.0,
                0.0
            ],
            "_ParamId": 0,
            "_QuestID": "null",
            "_StatusID": "None",
            "_TimeZone": 15
        },
        "B": 1
    }
}